Workbook

Sheet COMECE AQUI
A1: VIDA FINANCEIRA — FREE
A3: Controle suas receitas e despesas e veja seu resultado mensal.
A5: COMECE EM 2 MINUTOS
A7: 1 | B7: Lançamentos | D7: Cadastre receitas e despesas.
A8: 2 | B8: Dashboard | D8: Veja receitas, despesas, resultado e taxa de poupança.
A11: O QUE VOCÊ ENCONTRA NA FREE
A13: ✓ Cadastro de receitas e despesas
A14: ✓ Dashboard mensal
A15: ✓ Taxa de poupança
A16: ✓ Gráfico de despesas por categoria
A18: PREMIUM
A20: A versão Premium adiciona cartões e parcelas, contas, investimentos, patrimônio, metas, simuladores e planejamento. A Free é propositalmente simples para você começar.

Sheet LANÇAR
A1: LANÇAMENTO RÁPIDO
A3: Na versão Free, o jeito mais simples é registrar diretamente na aba Lançamentos.
A7: → ABRIR LANÇAMENTOS

Sheet LEIA-ME
A1: VIDA FINANCEIRA — Protótipo v1
A3: Objetivo | B3: Protótipo inicial de uma planilha comercial de controle financeiro e patrimonial.
A5: Como começar | B5: 1) Vá em Configurações e ajuste categorias, contas e cartões. 2) Lance receitas/despesas. 3) Cadastre investimentos e patrimônio. 4) Consulte o Dashboard.
A7: Importante | B7: Os dados atuais são exemplos e servem apenas para demonstrar o funcionamento. Substitua-os pelos seus dados.
A9: Próximas melhorias | B9: Versão comercial: acabamento visual, tela de boas-vindas, filtros por mês, parcelas avançadas, histórico patrimonial, proteção de fórmulas, manual do usuário e versão FREE/PREMIUM.

Sheet Dashboard
A1: VIDA FINANCEIRA — FREE
A2: Resumo mensal | G2: Mês: | H2: 46266
A4: RECEITAS | C4: DESPESAS | E4: RESULTADO | G4: TAXA DE POUPANÇA
A5: =SUMIFS(Lançamentos!$F$5:$F$304,Lançamentos!$B$5:$B$304,"Receita",Lançamentos!$A$5:$A$304,">="&$H$2,Lançamentos!$A$5:$A$304,"<"&EDATE($H$2,1)) -> 6000 | C5: =SUMIFS(Lançamentos!$F$5:$F$304,Lançamentos!$B$5:$B$304,"Despesa",Lançamentos!$A$5:$A$304,">="&$H$2,Lançamentos!$A$5:$A$304,"<"&EDATE($H$2,1)) -> 2450 | E5: =A5-C5 -> 3550 | G5: =IFERROR(E5/A5,0) -> 0.59166667
A8: DESPESAS POR CATEGORIA | C8: COMPARAÇÃO | D8: COMO USAR
C9: Maior gasto = barra máxima
A10: Moradia | B10: =SUMIFS(Lançamentos!$F$5:$F$304,Lançamentos!$C$5:$C$304,A10,Lançamentos!$B$5:$B$304,"Despesa",Lançamentos!$A$5:$A$304,">="&$H$2,Lançamentos!$A$5:$A$304,"<"&EDATE($H$2,1)) -> 700 | C10: =IF(B10=0,"",REPT("█",MAX(1,ROUND(B10/MAX($B$10:$B$19)*16,0)))) -> ████████████ | D10: 1. Escolha o mês. 2. Registre suas receitas e despesas. 3. Volte ao Dashboard. 4. Analise seu resultado e sua taxa de poupança.
A11: Alimentação | B11: =SUMIFS(Lançamentos!$F$5:$F$304,Lançamentos!$C$5:$C$304,A11,Lançamentos!$B$5:$B$304,"Despesa",Lançamentos!$A$5:$A$304,">="&$H$2,Lançamentos!$A$5:$A$304,"<"&EDATE($H$2,1)) -> 900 | C11: =IF(B11=0,"",REPT("█",MAX(1,ROUND(B11/MAX($B$10:$B$19)*16,0)))) -> ████████████████
A12: Transporte | B12: =SUMIFS(Lançamentos!$F$5:$F$304,Lançamentos!$C$5:$C$304,A12,Lançamentos!$B$5:$B$304,"Despesa",Lançamentos!$A$5:$A$304,">="&$H$2,Lançamentos!$A$5:$A$304,"<"&EDATE($H$2,1)) -> 400 | C12: =IF(B12=0,"",REPT("█",MAX(1,ROUND(B12/MAX($B$10:$B$19)*16,0)))) -> ███████
A13: Saúde | B13: =SUMIFS(Lançamentos!$F$5:$F$304,Lançamentos!$C$5:$C$304,A13,Lançamentos!$B$5:$B$304,"Despesa",Lançamentos!$A$5:$A$304,">="&$H$2,Lançamentos!$A$5:$A$304,"<"&EDATE($H$2,1)) -> 0 | C13: =IF(B13=0,"",REPT("█",MAX(1,ROUND(B13/MAX($B$10:$B$19)*16,0))))
A14: Educação | B14: =SUMIFS(Lançamentos!$F$5:$F$304,Lançamentos!$C$5:$C$304,A14,Lançamentos!$B$5:$B$304,"Despesa",Lançamentos!$A$5:$A$304,">="&$H$2,Lançamentos!$A$5:$A$304,"<"&EDATE($H$2,1)) -> 0 | C14: =IF(B14=0,"",REPT("█",MAX(1,ROUND(B14/MAX($B$10:$B$19)*16,0))))
A15: Lazer | B15: =SUMIFS(Lançamentos!$F$5:$F$304,Lançamentos!$C$5:$C$304,A15,Lançamentos!$B$5:$B$304,"Despesa",Lançamentos!$A$5:$A$304,">="&$H$2,Lançamentos!$A$5:$A$304,"<"&EDATE($H$2,1)) -> 300 | C15: =IF(B15=0,"",REPT("█",MAX(1,ROUND(B15/MAX($B$10:$B$19)*16,0)))) -> █████
A16: Compras | B16: =SUMIFS(Lançamentos!$F$5:$F$304,Lançamentos!$C$5:$C$304,A16,Lançamentos!$B$5:$B$304,"Despesa",Lançamentos!$A$5:$A$304,">="&$H$2,Lançamentos!$A$5:$A$304,"<"&EDATE($H$2,1)) -> 0 | C16: =IF(B16=0,"",REPT("█",MAX(1,ROUND(B16/MAX($B$10:$B$19)*16,0)))) | D16: PREMIUM
A17: Assinaturas | B17: =SUMIFS(Lançamentos!$F$5:$F$304,Lançamentos!$C$5:$C$304,A17,Lançamentos!$B$5:$B$304,"Despesa",Lançamentos!$A$5:$A$304,">="&$H$2,Lançamentos!$A$5:$A$304,"<"&EDATE($H$2,1)) -> 0 | C17: =IF(B17=0,"",REPT("█",MAX(1,ROUND(B17/MAX($B$10:$B$19)*16,0))))
A18: Impostos | B18: =SUMIFS(Lançamentos!$F$5:$F$304,Lançamentos!$C$5:$C$304,A18,Lançamentos!$B$5:$B$304,"Despesa",Lançamentos!$A$5:$A$304,">="&$H$2,Lançamentos!$A$5:$A$304,"<"&EDATE($H$2,1)) -> 0 | C18: =IF(B18=0,"",REPT("█",MAX(1,ROUND(B18/MAX($B$10:$B$19)*16,0)))) | D18: Cartões • Contas • Investimentos • Patrimônio • Metas • Simuladores • Planejamento
A19: Outros | B19: =SUMIFS(Lançamentos!$F$5:$F$304,Lançamentos!$C$5:$C$304,A19,Lançamentos!$B$5:$B$304,"Despesa",Lançamentos!$A$5:$A$304,">="&$H$2,Lançamentos!$A$5:$A$304,"<"&EDATE($H$2,1)) -> 0 | C19: =IF(B19=0,"",REPT("█",MAX(1,ROUND(B19/MAX($B$10:$B$19)*16,0))))

Sheet Configurações
A1: CONFIGURAÇÕES
A2: ← Comece aqui
A4: Categorias de receita | B4: Categorias de despesa | C4: Contas | D4: Cartões | E4: Tipos de investimento | F4: Tipos de patrimônio
A5: Salário | B5: Moradia | C5: Conta Corrente | D5: Cartão Principal | E5: Renda Fixa | F5: Dinheiro
A6: Freelance | B6: Alimentação | C6: Conta Poupança | D6: Nubank | E6: Ações | F6: Veículo
A7: Outras receitas | B7: Transporte | C7: Carteira | D7: Outro cartão | E7: ETF | F7: Imóvel
B8: Saúde | E8: Fundos | F8: Previdência
B9: Lazer | E9: Cripto | F9: Outros ativos
B10: Educação | F10: Dívida
B11: Compras | F11: Empréstimo
B12: Assinaturas | F12: Financiamento
B13: Impostos | F13: Outros passivos
B14: Outros

Sheet Lançamentos
A1: LANÇAMENTOS — FREE
A2: Registre receitas e despesas. A mesma compra não deve ser lançada duas vezes.
A4: Data | B4: Tipo | C4: Categoria | D4: Descrição | E4: Conta | F4: Valor | G4: Observação
A5: 46266 | B5: Receita | C5: Salário | D5: Salário mensal | E5: Conta principal | F5: 6000
A6: 46267 | B6: Despesa | C6: Moradia | D6: Condomínio | E6: Conta principal | F6: 700
A7: 46268 | B7: Despesa | C7: Alimentação | D7: Supermercado | E7: Conta principal | F7: 900
A8: 46270 | B8: Despesa | C8: Transporte | D8: Combustível | E8: Conta principal | F8: 400
A9: 46272 | B9: Despesa | C9: Lazer | D9: Passeio | E9: Conta principal | F9: 300
A10: 46275 | B10: Despesa | C10: Contas | D10: Internet | E10: Conta principal | F10: 150

Sheet Cartões
A1: CARTÕES DE CRÉDITO
A2: ← Comece aqui
A4: Data da compra | B4: Cartão | C4: Descrição | D4: Categoria | E4: Valor total | F4: Parcelas | G4: 1ª parcela | H4: Valor da parcela | I4: Observação
H5: =IFERROR(E5/F5,0) -> 0
H6: =IFERROR(E6/F6,0) -> 0
H7: =IFERROR(E7/F7,0) -> 0
H8: =IFERROR(E8/F8,0) -> 0
H9: =IFERROR(E9/F9,0) -> 0
H10: =IFERROR(E10/F10,0) -> 0
H11: =IFERROR(E11/F11,0) -> 0
H12: =IFERROR(E12/F12,0) -> 0
H13: =IFERROR(E13/F13,0) -> 0
H14: =IFERROR(E14/F14,0) -> 0
H15: =IFERROR(E15/F15,0) -> 0
H16: =IFERROR(E16/F16,0) -> 0
... H204: =IFERROR(E204/F204,0) -> 0

Sheet Contas
A1: CONTAS
A2: ← Comece aqui
A4: Conta | B4: Observação | C4: Saldo inicial | D4: Receitas | E4: Despesas | F4: Saldo estimado
D5: =SUMIFS(Lançamentos!$F$5:$F$504,Lançamentos!$E$5:$E$504,$A5,Lançamentos!$B$5:$B$504,"Receita") -> 0 | E5: =SUMIFS(Lançamentos!$F$5:$F$504,Lançamentos!$E$5:$E$504,$A5,Lançamentos!$B$5:$B$504,"Despesa") -> 0 | F5: =C5+D5-E5 -> 0
D6: =SUMIFS(Lançamentos!$F$5:$F$504,Lançamentos!$E$5:$E$504,$A6,Lançamentos!$B$5:$B$504,"Receita") -> 0 | E6: =SUMIFS(Lançamentos!$F$5:$F$504,Lançamentos!$E$5:$E$504,$A6,Lançamentos!$B$5:$B$504,"Despesa") -> 0 | F6: =C6+D6-E6 -> 0
D7: =SUMIFS(Lançamentos!$F$5:$F$504,Lançamentos!$E$5:$E$504,$A7,Lançamentos!$B$5:$B$504,"Receita") -> 0 | E7: =SUMIFS(Lançamentos!$F$5:$F$504,Lançamentos!$E$5:$E$504,$A7,Lançamentos!$B$5:$B$504,"Despesa") -> 0 | F7: =C7+D7-E7 -> 0
D8: =SUMIFS(Lançamentos!$F$5:$F$504,Lançamentos!$E$5:$E$504,$A8,Lançamentos!$B$5:$B$504,"Receita") -> 0 | E8: =SUMIFS(Lançamentos!$F$5:$F$504,Lançamentos!$E$5:$E$504,$A8,Lançamentos!$B$5:$B$504,"Despesa") -> 0 | F8: =C8+D8-E8 -> 0
D9: =SUMIFS(Lançamentos!$F$5:$F$504,Lançamentos!$E$5:$E$504,$A9,Lançamentos!$B$5:$B$504,"Receita") -> 0 | E9: =SUMIFS(Lançamentos!$F$5:$F$504,Lançamentos!$E$5:$E$504,$A9,Lançamentos!$B$5:$B$504,"Despesa") -> 0 | F9: =C9+D9-E9 -> 0
D10: =SUMIFS(Lançamentos!$F$5:$F$504,Lançamentos!$E$5:$E$504,$A10,Lançamentos!$B$5:$B$504,"Receita") -> 0 | E10: =SUMIFS(Lançamentos!$F$5:$F$504,Lançamentos!$E$5:$E$504,$A10,Lançamentos!$B$5:$B$504,"Despesa") -> 0 | F10: =C10+D10-E10 -> 0
D11: =SUMIFS(Lançamentos!$F$5:$F$504,Lançamentos!$E$5:$E$504,$A11,Lançamentos!$B$5:$B$504,"Receita") -> 0 | E11: =SUMIFS(Lançamentos!$F$5:$F$504,Lançamentos!$E$5:$E$504,$A11,Lançamentos!$B$5:$B$504,"Despesa") -> 0 | F11: =C11+D11-E11 -> 0
D12: =SUMIFS(Lançamentos!$F$5:$F$504,Lançamentos!$E$5:$E$504,$A12,Lançamentos!$B$5:$B$504,"Receita") -> 0 | E12: =SUMIFS(Lançamentos!$F$5:$F$504,Lançamentos!$E$5:$E$504,$A12,Lançamentos!$B$5:$B$504,"Despesa") -> 0 | F12: =C12+D12-E12 -> 0
D13: =SUMIFS(Lançamentos!$F$5:$F$504,Lançamentos!$E$5:$E$504,$A13,Lançamentos!$B$5:$B$504,"Receita") -> 0 | E13: =SUMIFS(Lançamentos!$F$5:$F$504,Lançamentos!$E$5:$E$504,$A13,Lançamentos!$B$5:$B$504,"Despesa") -> 0 | F13: =C13+D13-E13 -> 0
D14: =SUMIFS(Lançamentos!$F$5:$F$504,Lançamentos!$E$5:$E$504,$A14,Lançamentos!$B$5:$B$504,"Receita") -> 0 | E14: =SUMIFS(Lançamentos!$F$5:$F$504,Lançamentos!$E$5:$E$504,$A14,Lançamentos!$B$5:$B$504,"Despesa") -> 0 | F14: =C14+D14-E14 -> 0
D15: =SUMIFS(Lançamentos!$F$5:$F$504,Lançamentos!$E$5:$E$504,$A15,Lançamentos!$B$5:$B$504,"Receita") -> 0 | E15: =SUMIFS(Lançamentos!$F$5:$F$504,Lançamentos!$E$5:$E$504,$A15,Lançamentos!$B$5:$B$504,"Despesa") -> 0 | F15: =C15+D15-E15 -> 0
D16: =SUMIFS(Lançamentos!$F$5:$F$504,Lançamentos!$E$5:$E$504,$A16,Lançamentos!$B$5:$B$504,"Receita") -> 0 | E16: =SUMIFS(Lançamentos!$F$5:$F$504,Lançamentos!$E$5:$E$504,$A16,Lançamentos!$B$5:$B$504,"Despesa") -> 0 | F16: =C16+D16-E16 -> 0
... D34: =SUMIFS(Lançamentos!$F$5:$F$504,Lançamentos!$E$5:$E$504,$A34,Lançamentos!$B$5:$B$504,"Receita") -> 0 | E34: =SUMIFS(Lançamentos!$F$5:$F$504,Lançamentos!$E$5:$E$504,$A34,Lançamentos!$B$5:$B$504,"Despesa") -> 0 | F34: =C34+D34-E34 -> 0

Sheet Investimentos
A1: INVESTIMENTOS
A2: Cadastre cada posição. A rentabilidade é calculada automaticamente: (valor atual ÷ valor investido) − 1.
A4: Ativo | B4: Classe | C4: Descrição | D4: Data | E4: Valor investido | F4: Valor atual | G4: Rentabilidade | H4: Peso na carteira | I4: Observação | K4: RESUMO DA CARTEIRA
G5: =IFERROR(F5/E5-1,0) -> 0 | H5: =IFERROR(F5/SUM($F$5:$F$104),0) -> 0 | K5: Valor investido | L5: =SUM(E5:E104) -> 0
G6: =IFERROR(F6/E6-1,0) -> 0 | H6: =IFERROR(F6/SUM($F$5:$F$104),0) -> 0 | K6: Valor atual | L6: =SUM(F5:F104) -> 0
G7: =IFERROR(F7/E7-1,0) -> 0 | H7: =IFERROR(F7/SUM($F$5:$F$104),0) -> 0 | K7: Rentabilidade total | L7: =IFERROR(L6/L5-1,0) -> 0
G8: =IFERROR(F8/E8-1,0) -> 0 | H8: =IFERROR(F8/SUM($F$5:$F$104),0) -> 0 | K8: Ativos cadastrados | L8: =COUNTIF(A5:A104,"<>") -> 0
G9: =IFERROR(F9/E9-1,0) -> 0 | H9: =IFERROR(F9/SUM($F$5:$F$104),0) -> 0
G10: =IFERROR(F10/E10-1,0) -> 0 | H10: =IFERROR(F10/SUM($F$5:$F$104),0) -> 0
G11: =IFERROR(F11/E11-1,0) -> 0 | H11: =IFERROR(F11/SUM($F$5:$F$104),0) -> 0
G12: =IFERROR(F12/E12-1,0) -> 0 | H12: =IFERROR(F12/SUM($F$5:$F$104),0) -> 0
G13: =IFERROR(F13/E13-1,0) -> 0 | H13: =IFERROR(F13/SUM($F$5:$F$104),0) -> 0
G14: =IFERROR(F14/E14-1,0) -> 0 | H14: =IFERROR(F14/SUM($F$5:$F$104),0) -> 0
G15: =IFERROR(F15/E15-1,0) -> 0 | H15: =IFERROR(F15/SUM($F$5:$F$104),0) -> 0
G16: =IFERROR(F16/E16-1,0) -> 0 | H16: =IFERROR(F16/SUM($F$5:$F$104),0) -> 0
G17: =IFERROR(F17/E17-1,0) -> 0 | H17: =IFERROR(F17/SUM($F$5:$F$104),0) -> 0
G18: =IFERROR(F18/E18-1,0) -> 0 | H18: =IFERROR(F18/SUM($F$5:$F$104),0) -> 0
G19: =IFERROR(F19/E19-1,0) -> 0 | H19: =IFERROR(F19/SUM($F$5:$F$104),0) -> 0
G20: =IFERROR(F20/E20-1,0) -> 0 | H20: =IFERROR(F20/SUM($F$5:$F$104),0) -> 0
... G104: =IFERROR(F104/E104-1,0) -> 0 | H104: =IFERROR(F104/SUM($F$5:$F$104),0) -> 0

Sheet Patrimônio
A1: PATRIMÔNIO
A2: ← Comece aqui
A4: Tipo | B4: Categoria | C4: Descrição | D4: Valor atual | E4: Observação | G4: RESUMO
G5: Total de ativos | H5: =SUMIF($A$5:$A$104,"Ativo",$D$5:$D$104) -> 0
G6: Total de passivos | H6: =SUMIF($A$5:$A$104,"Passivo",$D$5:$D$104) -> 0
G7: Patrimônio líquido | H7: =H5-H6 -> 0

Sheet Metas
A1: METAS FINANCEIRAS
A2: ← Comece aqui
A4: Meta | B4: Valor alvo | C4: Valor atual | D4: Progresso | E4: Prazo | F4: Observação
D5: =IFERROR(C5/B5,0) -> 0
D6: =IFERROR(C6/B6,0) -> 0
D7: =IFERROR(C7/B7,0) -> 0
D8: =IFERROR(C8/B8,0) -> 0
D9: =IFERROR(C9/B9,0) -> 0
D10: =IFERROR(C10/B10,0) -> 0
D11: =IFERROR(C11/B11,0) -> 0
D12: =IFERROR(C12/B12,0) -> 0
D13: =IFERROR(C13/B13,0) -> 0
D14: =IFERROR(C14/B14,0) -> 0
D15: =IFERROR(C15/B15,0) -> 0
D16: =IFERROR(C16/B16,0) -> 0
... D54: =IFERROR(C54/B54,0) -> 0

Sheet Simuladores
A1: Simuladores Financeiros
A2: ← Comece aqui
A3: Use os campos de entrada para testar cenários. Os resultados são estimativas matemáticas.
A5: Valor inicial | B5: 10000
A6: Aporte mensal | B6: 1000
A7: Rentabilidade mensal | B7: 0.008
A8: Prazo (meses) | B8: 120
A10: Total investido | B10: =B5+B6*B8 -> 130000
A11: Rendimentos | B11: =B12-B10 -> 96234.867
A12: Patrimônio final | B12: =B5*(1+B7)^B8+B6*(((1+B7)^B8-1)/B7) -> 226234.87
A15: Planejamento de Meta
A17: Valor da meta | B17: 100000
A18: Valor atual | B18: 20000
A19: Prazo (meses) | B19: 48
A20: Aporte mensal necessário | B20: =IFERROR((B17-B18)/B19,0) -> 1666.6667

Sheet Planejamento
A1: Planejamento Mensal
A2: ← Comece aqui
A3: Categoria | B3: Orçamento | C3: Realizado | D3: Diferença | E3: % Utilizado | F3: Status
A4: Moradia | B4: 0 | C4: =SUMIFS(Lançamentos!$F$4:$F$503,Lançamentos!$C$4:$C$503,A4,Lançamentos!$B$4:$B$503,"Despesa") -> 700 | D4: =B4-C4 -> -700 | E4: =IFERROR(C4/B4,0) -> 0 | F4: =IF(E4<=1,"Dentro","Acima") -> Dentro
A5: Alimentação | B5: 0 | C5: =SUMIFS(Lançamentos!$F$4:$F$503,Lançamentos!$C$4:$C$503,A5,Lançamentos!$B$4:$B$503,"Despesa") -> 900 | D5: =B5-C5 -> -900 | E5: =IFERROR(C5/B5,0) -> 0 | F5: =IF(E5<=1,"Dentro","Acima") -> Dentro
A6: Transporte | B6: 0 | C6: =SUMIFS(Lançamentos!$F$4:$F$503,Lançamentos!$C$4:$C$503,A6,Lançamentos!$B$4:$B$503,"Despesa") -> 400 | D6: =B6-C6 -> -400 | E6: =IFERROR(C6/B6,0) -> 0 | F6: =IF(E6<=1,"Dentro","Acima") -> Dentro
A7: Saúde | B7: 0 | C7: =SUMIFS(Lançamentos!$F$4:$F$503,Lançamentos!$C$4:$C$503,A7,Lançamentos!$B$4:$B$503,"Despesa") -> 0 | D7: =B7-C7 -> 0 | E7: =IFERROR(C7/B7,0) -> 0 | F7: =IF(E7<=1,"Dentro","Acima") -> Dentro
A8: Educação | B8: 0 | C8: =SUMIFS(Lançamentos!$F$4:$F$503,Lançamentos!$C$4:$C$503,A8,Lançamentos!$B$4:$B$503,"Despesa") -> 0 | D8: =B8-C8 -> 0 | E8: =IFERROR(C8/B8,0) -> 0 | F8: =IF(E8<=1,"Dentro","Acima") -> Dentro
A9: Lazer | B9: 0 | C9: =SUMIFS(Lançamentos!$F$4:$F$503,Lançamentos!$C$4:$C$503,A9,Lançamentos!$B$4:$B$503,"Despesa") -> 300 | D9: =B9-C9 -> -300 | E9: =IFERROR(C9/B9,0) -> 0 | F9: =IF(E9<=1,"Dentro","Acima") -> Dentro
A10: Compras | B10: 0 | C10: =SUMIFS(Lançamentos!$F$4:$F$503,Lançamentos!$C$4:$C$503,A10,Lançamentos!$B$4:$B$503,"Despesa") -> 0 | D10: =B10-C10 -> 0 | E10: =IFERROR(C10/B10,0) -> 0 | F10: =IF(E10<=1,"Dentro","Acima") -> Dentro
A11: Assinaturas | B11: 0 | C11: =SUMIFS(Lançamentos!$F$4:$F$503,Lançamentos!$C$4:$C$503,A11,Lançamentos!$B$4:$B$503,"Despesa") -> 0 | D11: =B11-C11 -> 0 | E11: =IFERROR(C11/B11,0) -> 0 | F11: =IF(E11<=1,"Dentro","Acima") -> Dentro
A12: Impostos | B12: 0 | C12: =SUMIFS(Lançamentos!$F$4:$F$503,Lançamentos!$C$4:$C$503,A12,Lançamentos!$B$4:$B$503,"Despesa") -> 0 | D12: =B12-C12 -> 0 | E12: =IFERROR(C12/B12,0) -> 0 | F12: =IF(E12<=1,"Dentro","Acima") -> Dentro
A13: Outros | B13: 0 | C13: =SUMIFS(Lançamentos!$F$4:$F$503,Lançamentos!$C$4:$C$503,A13,Lançamentos!$B$4:$B$503,"Despesa") -> 0 | D13: =B13-C13 -> 0 | E13: =IFERROR(C13/B13,0) -> 0 | F13: =IF(E13<=1,"Dentro","Acima") -> Dentro

Sheet Histórico Patrimonial
A1: EVOLUÇÃO DO PATRIMÔNIO
A2: ← Comece aqui
A3: Mês | B3: Ativos | C3: Passivos | D3: Patrimônio Líquido
A4: 46113 | B4: 600000 | C4: 360000 | D4: =B4-C4 -> 240000
A5: 46143 | B5: 625000 | C5: 355000 | D5: =B5-C5 -> 270000
A6: 46174 | B6: 650000 | C6: 350000 | D6: =B6-C6 -> 300000
A7: 46204 | B7: 670000 | C7: 345000 | D7: =B7-C7 -> 325000
A8: 46235 | B8: 695000 | C8: 340000 | D8: =B8-C8 -> 355000
A9: 46266 | B9: 710000 | C9: 370000 | D9: =B9-C9 -> 340000
A11: Como usar
A12: Registre uma linha ao fim de cada mês para acompanhar a evolução do patrimônio líquido.
